LICENSE
README.md
setup.cfg
setup.py
NitroFE/__init__.py
NitroFE.egg-info/PKG-INFO
NitroFE.egg-info/SOURCES.txt
NitroFE.egg-info/dependency_links.txt
NitroFE.egg-info/requires.txt
NitroFE.egg-info/top_level.txt
NitroFE.egg-info/zip-safe
NitroFE/encoding/__init__.py
NitroFE/encoding/encoding_features.py
NitroFE/time_based_features/__init__.py
NitroFE/time_based_features/indicator_features/_AbsolutePriceOscillator.py
NitroFE/time_based_features/indicator_features/_AroonOscillator.py
NitroFE/time_based_features/indicator_features/_AverageDirectionalMovementIndex.py
NitroFE/time_based_features/indicator_features/_AverageTrueRange.py
NitroFE/time_based_features/indicator_features/_BollingerBands.py
NitroFE/time_based_features/indicator_features/_ElasticSeriesWeightedAverage.py
NitroFE/time_based_features/indicator_features/_InverseFisherRelativeStrengthIndex.py
NitroFE/time_based_features/indicator_features/_KaufmanEfficiency.py
NitroFE/time_based_features/indicator_features/_KeltnerChannel.py
NitroFE/time_based_features/indicator_features/_MovingAverageConvergenceDivergence.py
NitroFE/time_based_features/indicator_features/_PercentageValueOscillator.py
NitroFE/time_based_features/indicator_features/_RelativeStrengthIndex.py
NitroFE/time_based_features/indicator_features/_SeriesWeightedAverage.py
NitroFE/time_based_features/indicator_features/_SeriesWeightedMovingFeature.py
NitroFE/time_based_features/indicator_features/_TripleExponentialMovingAverageOscillator.py
NitroFE/time_based_features/indicator_features/_TypicalValue.py
NitroFE/time_based_features/indicator_features/_ZeroLagExponentialMovingFeature.py
NitroFE/time_based_features/indicator_features/__init__.py
NitroFE/time_based_features/moving_average_features/__init__.py
NitroFE/time_based_features/moving_average_features/moving_average_features.py
NitroFE/time_based_features/weighted_window_features/__init__.py
NitroFE/time_based_features/weighted_window_features/weighted_rolling_window_engine.py
NitroFE/time_based_features/weighted_window_features/weighted_window_features.py
NitroFE/time_based_features/weighted_window_features/weighted_windows.py