Metadata-Version: 2.1
Name: NitroFE
Version: 0.0.9
Summary: NitroFE is a Python feature engineering engine which provides a variety of feature engineering modules designed to handle continous calcualtion.
Home-page: https://github.com/NITRO-AI/NitroFE
Author: Nitro-AI
Author-email: nitro.ai.solutions@gmail.com
License: Apache License 2.0
Platform: UNKNOWN
